<params>
	<param key = 'layer' value = '2' />
	<param key = 'type' value = 'overworld' />
</params>
<planes>
	<plane name = 'Untitled Plane' x = '0' y = '0' modal = '0'>
		<structure>
			0 0 0 0 0 0 0 0 0 0 152 198 0 0 0 0 0 0 0 0 153 184 0 0 0 0 0 0 0 0 191 0 0 0 0 0 0 0 192 196 0 0 
			196 183 0 0 187 25 154 182 0 154 192 0 0 0 0 0 0 186 182 152 193 177 0 0 154 181 185 0 0 190 165 0 0 0 0 0 0 0 0 0 0 0 
			167 178 184 0 179 0 154 0 0 152 0 0 0 0 190 0 0 0 0 153 0 0 0 152 188 170 0 0 0 179 0 0 0 0 154 195 189 153 0 0 0 0 
			0 0 0 0 0 154 189 23 187 191 153 0 0 190 177 0 188 0 188 196 153 189 0 0 0 0 0 0 0 178 197 0 0 199 152 0 163 196 154 0 0 0 
			0 0 0 0 199 154 0 0 0 0 0 0 0 179 0 0 160 0 0 0 154 165 189 0 0 185 185 154 0 0 0 0 0 175 154 0 0 0 153 0 0 0 
			0 0 198 0 165 154 0 199 187 0 152 0 0 161 190 0 170 199 0 0 0 0 0 0 0 0 169 195 154 0 0 0 0 0 153 190 198 154 199 0 0 0 
			183 0 178 0 175 184 154 0 0 0 153 0 0 0 0 0 0 0 0 0 0 189 0 0 0 0 0 0 0 0 0 0 154 185 152 179 0 154 0 0 188 0 
			161 0 0 0 162 170 197 153 0 0 0 188 0 0 0 0 187 184 153 0 0 166 0 0 0 154 198 184 0 0 0 0 0 0 0 0 0 0 0 182 172 0 
			0 0 0 0 0 0 0 0 0 0 0 0 0 0 0 0 0 160 189 154 0 163 184 0 153 193 174 0 0 154 196 190 0 0 0 0 0 0 0 0 173 0 
			0 198 0 186 0 0 0 0 0 192 191 154 0 0 195 0 0 0 0 0 0 0 0 0 0 0 0 0 152 198 167 0 0 0 0 0 0 0 191 0 0 0 
			198 167 0 171 0 186 196 154 0 0 175 196 154 0 178 0 0 0 0 0 0 0 0 153 191 0 0 0 0 0 0 0 0 197 197 192 0 186 170 0 0 0 
			179 0 0 0 0 0 171 190 152 0 0 0 0 0 0 0 0 187 28 153 197 0 152 193 175 0 0 192 198 181 0 0 0 160 165 0 0 0 173 0 0 0 
			160 184 0 0 0 0 0 0 0 0 0 0 0 184 189 154 0 179 0 153 0 0 153 0 0 0 0 0 0 0 0 0 0 0 0 0 0 0 0 0 0 0 
			0 0 0 196 0 0 199 28 24 183 28 186 0 0 169 154 0 0 154 181 27 193 193 152 0 0 0 0 199 192 180 0 0 184 184 154 199 187 217 190 0 0 
			0 0 181 164 180 0 0 0 0 0 0 0 0 0 0 0 0 187 154 0 0 0 0 154 0 0 0 0 0 0 0 0 0 0 182 154 198 0 0 0 0 0 
			0 0 0 0 0 0 0 0 0 0 0 191 0 182 184 0 0 176 154 0 199 187 0 0 0 187 182 154 0 0 180 187 0 0 0 153 0 0 0 0 0 0 
			0 154 189 0 193 198 154 0 0 193 0 177 0 163 174 189 0 0 0 0 0 0 0 154 0 0 166 182 152 0 166 173 191 0 0 152 198 195 219 182 0 0 
			152 190 171 0 0 163 185 154 0 179 0 0 0 0 0 0 0 172 163 185 152 180 28 154 186 0 0 0 0 0 0 0 0 0 153 184 195 0 0 0 0 0 
			0 0 0 0 0 0 0 0 0 0 0 0 0 0 0 0 0 0 0 0 0 0 0 0 0 0 0 0 154 188 154 0 0 0 0 0 0 0 196 194 190 0 
			0 0 0 183 194 154 199 192 216 190 0 0 0 0 0 0 0 0 0 0 0 0 0 0 0 0 0 0 153 167 198 0 184 0 188 190 198 0 0 178 173 0 
			0 0 0 0 197 152 197 0 0 0 0 0 182 185 182 152 0 0 182 191 192 152 0 0 192 196 0 152 199 179 0 0 178 0 174 167 0 0 0 0 0 0 
			0 0 0 0 0 154 0 0 0 0 0 0 0 0 164 190 0 0 0 0 171 194 0 0 0 0 0 0 0 0 0 0 0 0 0 0 0 0 199 194 185 0 
			193 198 189 0 0 152 189 185 219 186 0 0 0 0 0 0 0 153 180 0 0 0 0 0 0 0 0 0 0 0 0 0 0 0 154 188 154 0 0 0 0 0 
			0 165 162 0 154 199 199 0 0 0 0 0 0 0 180 0 153 195 165 0 0 0 0 194 189 152 199 187 218 188 0 0 0 0 152 172 184 0 0 187 181 0 
			0 0 0 0 0 0 0 0 0 0 0 0 0 199 163 0 0 0 0 0 0 0 0 0 188 154 194 0 0 0 0 0 0 152 199 179 0 0 0 0 0 0 
			0 0 0 0 0 0 0 0 196 188 0 0 0 179 0 0 189 180 183 0 0 182 0 0 0 154 0 0 0 0 0 0 0 0 0 0 0 0 0 188 185 0 
			0 0 0 0 0 182 0 0 163 160 189 0 0 175 194 0 0 169 177 0 0 177 0 0 0 152 189 189 219 183 0 0 0 0 0 0 0 0 0 0 0 0 
			0 170 194 152 0 168 0 0 0 0 0 0 0 0 0 0 0 0 0 0 0 177 189 0 154 197 183 0 0 0 0 0 0 192 0 0 0 186 189 194 0 0 
			0 0 0 0 0 163 198 0 0 0 0 0 0 0 0 0 0 0 0 0 0 0 0 0 0 0 0 0 0 0 0 0 184 177 0 0 0 0 178 174 0 0 
			0 0 0 0 0 0 0 0 0 0 0 152 186 198 0 0 195 182 182 0 194 0 0 186 152 0 0 0 153 199 198 0 179 0 0 198 191 0 0 0 0 0 
			0 180 197 199 0 0 0 0 154 189 0 182 173 0 0 0 0 169 168 0 167 0 0 176 182 154 0 153 188 168 0 0 165 186 0 0 0 0 0 192 0 0 
			0 0 160 163 0 180 181 152 195 162 0 0 0 0 0 0 0 0 0 0 164 181 0 0 0 0 0 0 0 0 0 0 0 0 0 153 185 0 199 169 0 0 
			0 0 0 0 0 0 0 154 0 0 0 0 0 198 0 199 198 197 0 0 0 0 0 0 0 0 0 153 187 186 0 0 184 187 153 182 175 0 179 0 0 0 
			0 0 0 0 0 0 188 195 152 194 0 0 194 179 0 0 0 0 0 0 199 0 0 0 29 180 0 154 176 0 0 0 0 0 152 0 0 0 165 189 0 0 
			188 198 195 0 188 0 0 0 154 179 189 0 0 169 0 195 197 154 0 0 0 0 0 0 0 0 0 0 0 0 198 0 0 184 194 154 198 0 0 0 0 0 
			174 178 0 0 174 0 0 0 0 0 0 0 0 0 0 0 169 180 154 0 0 199 185 192 0 189 194 0 0 186 177 183 0 0 0 154 161 193 0 0 0 0 
			0 0 0 0 0 0 0 0 0 0 0 0 0 0 0 0 0 0 0 0 0 0 0 0 0 0 0 0 0 0 0 0 0 0 0 0 0 0 0 0 0 0 
		</structure>
	</plane>
</planes>
<entities>
</entities>
<triggers>
</triggers>
<scripts />
