<params>
	<param key = 'layer' value = '2' />
	<param key = 'type' value = 'overworld' />
</params>
<planes>
	<plane name = 'Untitled Plane' x = '0' y = '0' modal = '0'>
		<structure>
			0 0 154 228 223 0 0 154 224 228 0 222 224 0 0 224 225 0 0 0 0 228 222 228 0 0 0 0 0 0 226 225 0 0 222 0 222 0 0 0 0 0 0 0 
			0 154 223 205 0 0 153 228 204 0 0 0 0 0 0 0 0 0 0 0 0 0 228 205 0 220 225 227 0 0 0 0 0 0 205 0 203 0 0 220 222 153 0 0 
			0 0 0 0 0 0 0 0 0 0 0 0 0 154 0 0 0 218 220 220 154 0 0 0 0 0 0 0 0 0 0 0 0 0 0 0 200 223 0 0 205 220 223 0 
			0 0 0 0 0 0 0 0 225 221 228 0 154 225 153 0 217 0 0 205 226 154 0 220 224 220 0 0 228 223 154 225 226 218 224 0 0 0 0 0 0 205 0 0 
			0 0 0 0 0 0 0 0 202 203 0 0 152 204 227 154 0 0 0 200 203 0 0 0 0 0 0 0 0 202 152 202 0 0 0 0 0 0 0 0 0 0 0 0 
			0 227 27 29 226 24 226 0 0 0 0 0 154 0 202 225 154 0 0 0 0 153 0 0 223 227 154 0 0 0 152 0 0 0 0 0 0 154 220 154 0 0 0 0 
			0 0 0 0 0 0 0 0 0 0 0 0 154 0 0 203 221 153 222 0 0 225 154 0 0 202 227 227 0 0 154 225 226 219 220 0 0 152 201 221 0 0 0 0 
			0 0 0 228 225 153 0 0 223 223 228 0 154 0 0 0 0 154 0 0 0 0 152 0 0 0 205 0 0 153 226 201 0 0 0 0 152 226 204 0 0 0 0 0 
			223 228 0 0 201 226 152 0 0 226 205 0 0 0 224 222 0 0 0 0 0 0 0 0 224 0 0 0 0 0 0 0 0 0 0 0 0 0 0 0 152 226 226 0 
			202 204 225 0 0 0 0 0 0 0 0 0 0 0 0 0 0 0 0 0 227 225 0 0 200 0 222 225 0 0 0 0 0 0 0 152 220 222 0 152 221 202 0 0 
			0 0 0 0 0 0 0 0 0 0 0 0 0 0 226 223 152 0 225 0 203 203 226 0 0 0 0 0 0 0 153 221 224 0 152 228 201 0 0 0 0 0 0 0 
			0 0 0 0 154 221 223 0 0 0 224 225 228 0 0 201 154 0 204 0 0 0 0 0 0 220 223 223 152 0 152 204 0 0 0 0 0 0 0 226 227 152 0 0 
			0 0 0 0 154 0 0 0 0 0 0 221 205 0 0 0 0 0 200 225 0 0 0 0 0 0 0 205 226 0 0 0 0 0 154 224 221 0 0 0 204 220 153 0 
			153 227 200 0 154 227 0 152 224 223 0 0 0 0 0 0 0 0 0 0 0 0 0 0 0 228 0 0 0 0 0 0 0 0 222 205 0 0 0 0 0 0 0 0 
			152 0 0 154 224 200 0 153 203 0 0 0 0 154 224 154 0 0 153 222 226 0 0 0 227 202 0 218 226 222 154 0 0 0 0 0 0 225 224 154 0 0 0 0 
			153 223 226 221 204 0 0 0 0 0 0 0 0 154 202 224 0 152 228 205 0 0 227 0 0 0 0 0 0 205 228 153 0 220 228 217 0 0 205 224 154 0 0 0 
			153 0 0 202 205 228 0 154 228 154 0 0 154 222 201 0 0 0 0 0 0 0 204 0 202 228 0 0 0 0 0 153 224 205 0 0 0 0 0 0 0 0 223 0 
			0 0 0 0 0 0 0 153 201 226 0 0 0 0 0 0 0 0 0 221 0 0 0 0 0 0 0 0 0 0 222 154 0 0 0 0 0 0 0 0 0 223 205 0 
			200 228 223 221 154 0 152 224 202 0 0 0 0 0 0 0 226 154 0 201 0 0 153 224 228 0 0 219 152 226 203 227 226 220 153 0 0 221 227 153 0 200 0 0 
			0 0 0 0 0 0 0 0 0 0 227 0 0 0 228 218 205 228 0 0 0 0 222 203 0 0 0 0 153 0 0 200 0 0 152 224 0 0 203 154 0 201 221 0 
			0 0 0 0 0 0 0 0 0 226 200 0 218 228 200 0 204 0 0 221 219 0 0 0 0 0 0 0 0 0 0 0 0 0 0 0 0 0 0 0 0 0 0 0 
			0 0 0 0 0 0 0 0 0 0 201 0 0 154 203 0 201 221 153 205 0 0 223 227 152 0 0 0 0 0 0 221 225 228 153 0 0 0 0 226 227 223 0 0 
			0 0 228 0 0 0 154 221 220 0 0 0 0 0 0 0 0 204 154 205 0 0 0 205 225 226 0 0 0 0 0 0 0 205 224 0 0 0 0 205 204 0 0 0 
			0 222 204 0 0 154 226 200 0 0 0 0 0 154 0 0 0 0 153 202 221 0 0 0 205 0 0 153 222 220 0 0 0 0 0 0 224 204 0 0 0 0 0 0 
			0 0 205 0 0 0 0 0 0 152 221 0 219 228 228 154 227 228 223 205 205 0 221 0 0 0 0 153 202 0 0 228 225 228 0 0 0 200 0 154 224 220 0 0 
			0 0 0 0 224 226 0 0 154 223 205 0 0 0 0 0 0 0 0 0 0 0 204 0 0 0 0 0 0 0 0 0 222 205 0 0 0 0 0 228 202 0 0 0 
			0 0 0 0 0 0 0 0 0 0 0 0 0 0 0 0 0 0 0 0 0 0 0 0 0 0 0 0 0 0 0 0 0 0 0 0 0 0 0 0 0 0 0 0 
		</structure>
	</plane>
</planes>
<entities>
</entities>
<triggers>
</triggers>
<scripts />
