<params>
	<param key = 'layer' value = '2' />
	<param key = 'type' value = 'overworld' />
</params>
<planes>
	<plane name = 'Untitled Plane' x = '0' y = '0' modal = '0'>
		<structure>
			0 0 0 153 199 0 0 0 0 0 0 0 0 0 0 0 0 0 0 0 0 0 0 0 0 0 0 0 0 0 0 0 154 180 190 0 0 0 
			0 0 153 197 176 0 184 175 0 0 0 0 0 0 0 0 0 0 0 199 189 187 0 194 180 152 0 0 0 154 184 25 154 0 0 0 0 0 
			183 0 0 0 0 0 0 169 0 196 190 180 153 0 196 186 153 0 0 0 178 160 0 0 170 154 0 0 154 187 163 0 154 190 0 0 193 0 
			161 0 183 199 152 0 0 0 0 0 0 166 196 0 0 170 154 0 198 0 0 0 0 0 0 0 0 0 153 0 0 153 0 0 0 199 178 0 
			0 0 0 168 182 154 0 0 0 0 0 0 0 0 0 0 0 0 176 0 0 0 0 184 196 0 0 0 152 190 196 181 178 0 0 179 0 0 
			0 0 0 0 0 0 0 0 0 0 0 0 0 0 153 192 184 0 163 180 0 0 0 169 161 196 0 0 152 0 0 177 171 180 0 162 194 0 
			0 181 153 0 0 0 190 183 153 199 186 218 180 0 154 160 0 0 0 0 0 0 0 0 0 0 0 0 188 154 0 0 0 0 0 0 0 0 
			0 179 186 152 0 0 0 196 153 186 0 0 0 0 0 0 0 182 0 154 187 183 0 199 190 0 0 0 163 188 26 23 154 0 0 0 0 0 
			0 0 0 0 0 0 0 0 152 0 0 0 0 0 191 0 193 161 0 180 164 0 0 0 0 0 196 0 0 0 0 0 0 0 183 0 0 0 
			0 182 180 154 0 0 0 0 154 198 195 219 187 0 168 0 0 166 0 0 0 0 0 0 195 0 176 0 190 194 186 154 0 0 166 0 0 0 
			0 0 172 193 154 0 0 152 184 181 0 0 0 0 175 186 0 0 0 0 0 154 194 0 171 0 0 0 0 0 165 187 0 0 160 185 0 0 
			0 0 0 0 0 0 0 0 0 0 0 0 0 0 0 0 0 0 198 190 153 198 168 0 161 188 0 0 0 0 0 0 0 0 0 0 0 0 
			191 188 154 0 0 0 0 0 0 188 199 0 0 152 191 180 0 0 0 0 153 0 0 0 0 0 0 187 0 0 0 0 0 0 0 0 0 0 
			0 169 191 154 0 186 182 195 0 178 167 195 0 182 173 0 0 0 0 186 194 154 185 0 0 0 187 160 0 0 0 0 0 194 184 195 152 0 
			0 0 0 0 0 175 175 0 0 0 0 0 0 0 0 0 0 0 0 0 0 154 176 187 0 0 0 0 0 198 194 154 0 0 0 174 180 0 
			0 0 195 194 0 0 0 0 0 152 187 199 0 0 154 181 181 0 196 183 0 0 0 0 0 0 176 189 0 0 177 154 0 0 0 0 0 0 
			0 0 164 166 197 0 0 0 0 153 165 0 0 154 181 173 0 0 0 0 0 184 187 154 0 0 0 0 0 0 0 0 0 0 199 190 190 0 
			0 0 0 0 0 0 0 0 0 0 0 0 0 0 0 0 0 0 192 0 0 0 160 154 0 199 182 186 0 0 0 0 0 0 0 0 0 0 
			0 152 0 0 0 216 196 189 153 0 0 0 0 0 154 197 0 195 170 0 0 0 0 0 0 161 170 0 0 0 189 197 154 199 180 218 196 0 
			154 182 153 0 219 0 0 179 181 154 0 0 0 154 195 172 0 179 0 0 0 0 0 0 0 0 0 0 195 0 0 185 154 188 0 0 0 0 
			154 160 182 154 0 0 0 179 173 154 0 0 0 0 0 0 0 168 193 0 196 186 192 152 0 0 0 193 175 188 0 0 152 0 0 0 0 0 
			154 0 171 187 154 0 0 0 0 152 0 0 192 0 0 0 0 0 0 0 0 0 179 188 0 0 0 0 0 0 0 0 154 191 181 219 182 0 
			154 0 0 179 184 154 194 0 0 191 154 0 160 0 0 194 0 0 0 0 0 0 0 0 0 186 185 0 0 0 0 154 188 184 0 0 0 0 
			154 0 0 0 0 154 0 0 0 0 152 0 174 191 0 176 0 0 0 154 192 198 152 0 0 0 0 0 0 0 0 0 0 0 0 0 0 0 
			0 0 0 0 0 0 0 0 0 0 0 0 0 0 0 176 186 0 199 153 0 175 196 154 0 0 194 0 0 192 196 154 0 0 0 0 0 0 
			0 152 188 0 0 0 0 0 0 0 0 0 0 0 0 0 0 0 161 154 0 0 0 154 0 185 177 0 0 0 169 184 188 0 0 152 193 0 
			152 187 160 0 0 0 186 0 0 0 190 192 186 0 0 0 0 0 0 152 182 199 154 197 0 0 164 0 183 0 0 166 0 0 154 180 167 0 
			0 0 0 0 0 188 178 185 0 0 0 164 179 0 189 0 0 154 187 153 179 0 154 0 0 0 0 0 160 0 0 0 0 0 0 0 0 0 
			0 0 188 0 0 0 0 0 0 0 0 0 0 0 167 0 0 0 0 0 0 0 0 0 0 0 0 0 178 185 0 0 0 0 153 183 0 0 
			0 0 166 0 0 0 154 198 199 153 0 0 0 0 170 193 0 0 0 0 0 180 181 198 0 194 191 0 0 0 0 182 188 152 188 168 0 0 
			0 0 0 0 0 199 152 0 179 196 154 0 0 0 0 0 0 0 0 0 0 166 174 0 0 0 0 0 0 0 0 0 0 152 0 0 0 0 
			182 180 180 0 0 178 152 0 0 0 154 0 0 154 196 154 0 0 193 153 0 0 0 0 185 197 191 152 0 185 188 0 196 196 154 184 0 0 
			0 168 179 0 0 0 152 183 181 154 188 0 0 152 177 195 0 0 163 185 152 0 194 0 0 0 161 190 0 0 0 0 0 0 154 167 182 0 
			0 0 0 0 154 198 153 179 0 152 0 0 153 199 179 0 0 0 0 0 0 0 179 0 0 0 0 0 0 199 194 190 0 0 0 0 0 0 
			0 0 0 0 0 0 0 0 0 0 0 0 0 0 0 0 0 0 0 0 0 0 0 0 0 0 0 0 0 0 0 0 0 0 0 0 0 0 
		</structure>
	</plane>
</planes>
<entities>
</entities>
<triggers>
</triggers>
<scripts />
